{
    "Id": 3002052,
    "Name": "Lordly Trashcan",
    "Desc": "A peculiar entity born within the realm of fiction, its story documented in the nameless chronicles: A lone and valiant trashcan bearing the mission of the Garbage King to seek formidable warriors to eliminate all waste that threatens the world.",
    "MonsterCampID": null,
    "AttackBase": 18,
    "CriticalDamageBase": 0.20000000018626451,
    "DefenceBase": 210,
    "HPBase": 4650,
    "InitialDelayRatio": 1,
    "ImagePath": "SpriteOutput/MonsterFigure/Monster_3002052.png",
    "MinimumFatigueRatio": 0.20000000018626451,
    "Rank": "MinionLv2",
    "SpeedBase": 144,
    "StanceBase": 360,
    "StanceCount": 1,
    "StatusResistanceBase": 0.10000000009313226,
    "Child": [
        {
            "Id": 3002052,
            "AttackModifyRatio": 1,
            "DefenceModifyRatio": 1,
            "EliteGroup": 1,
            "HPModifyRatio": 3,
            "SpeedModifyRatio": 1,
            "SpeedModifyValue": -23.99999999976717,
            "StanceModifyRatio": 1,
            "StanceWeakList": [],
            "HardLevelGroup": 1,
            "DamageTypeResistance": [],
            "SkillList": [
                {
                    "Id": 300205201,
                    "SkillName": "The Can's Trials",
                    "SkillDesc": "Deals Physical DMG to a single target.",
                    "DamageType": "Physical",
                    "SPHitBase": ""
                },
                {
                    "Id": 300205202,
                    "SkillName": "The Can's Tribulations",
                    "SkillDesc": "Increases this unit's ATK. This effect is stackable and unremoveable.",
                    "DamageType": "",
                    "SPHitBase": ""
                },
                {
                    "Id": 300205203,
                    "SkillName": "The Can's Creed",
                    "SkillDesc": null,
                    "DamageType": "",
                    "SPHitBase": ""
                }
            ]
        },
        {
            "Id": 300205201,
            "AttackModifyRatio": 0.5000000004656613,
            "DefenceModifyRatio": 1,
            "EliteGroup": 1,
            "HPModifyRatio": 1.750000000698492,
            "SpeedModifyRatio": 1,
            "SpeedModifyValue": null,
            "StanceModifyRatio": 1,
            "StanceWeakList": [],
            "HardLevelGroup": 1,
            "DamageTypeResistance": [],
            "SkillList": [
                {
                    "Id": 300205201,
                    "SkillName": "The Can's Trials",
                    "SkillDesc": "Deals Physical DMG to a single target.",
                    "DamageType": "Physical",
                    "SPHitBase": ""
                },
                {
                    "Id": 300205202,
                    "SkillName": "The Can's Tribulations",
                    "SkillDesc": "Increases this unit's ATK. This effect is stackable and unremoveable.",
                    "DamageType": "",
                    "SPHitBase": ""
                },
                {
                    "Id": 300205203,
                    "SkillName": "The Can's Creed",
                    "SkillDesc": null,
                    "DamageType": "",
                    "SPHitBase": ""
                }
            ]
        }
    ],
    "Drop": [
        {
            "MonsterTemplateID": 3002052,
            "AvatarExpReward": 36,
            "DisplayItemList": [
                {
                    "$type": "ItemConfig",
                    "ID": 2
                },
                {
                    "$type": "ItemConfig",
                    "ID": 114001
                },
                {
                    "$type": "ItemConfig",
                    "ID": 181016
                }
            ]
        },
        {
            "MonsterTemplateID": 3002052,
            "WorldLevel": 1,
            "AvatarExpReward": 48,
            "DisplayItemList": [
                {
                    "$type": "ItemConfig",
                    "ID": 2
                },
                {
                    "$type": "ItemConfig",
                    "ID": 114001
                },
                {
                    "$type": "ItemConfig",
                    "ID": 181016
                }
            ]
        },
        {
            "MonsterTemplateID": 3002052,
            "WorldLevel": 2,
            "AvatarExpReward": 60,
            "DisplayItemList": [
                {
                    "$type": "ItemConfig",
                    "ID": 2
                },
                {
                    "$type": "ItemConfig",
                    "ID": 114001
                },
                {
                    "$type": "ItemConfig",
                    "ID": 114002
                },
                {
                    "$type": "ItemConfig",
                    "ID": 181016
                }
            ]
        },
        {
            "MonsterTemplateID": 3002052,
            "WorldLevel": 3,
            "AvatarExpReward": 72,
            "DisplayItemList": [
                {
                    "$type": "ItemConfig",
                    "ID": 2
                },
                {
                    "$type": "ItemConfig",
                    "ID": 114001
                },
                {
                    "$type": "ItemConfig",
                    "ID": 114002
                },
                {
                    "$type": "ItemConfig",
                    "ID": 181016
                }
            ]
        },
        {
            "MonsterTemplateID": 3002052,
            "WorldLevel": 4,
            "AvatarExpReward": 84,
            "DisplayItemList": [
                {
                    "$type": "ItemConfig",
                    "ID": 2
                },
                {
                    "$type": "ItemConfig",
                    "ID": 114001
                },
                {
                    "$type": "ItemConfig",
                    "ID": 114002
                },
                {
                    "$type": "ItemConfig",
                    "ID": 114003
                },
                {
                    "$type": "ItemConfig",
                    "ID": 181016
                }
            ]
        },
        {
            "MonsterTemplateID": 3002052,
            "WorldLevel": 5,
            "AvatarExpReward": 96,
            "DisplayItemList": [
                {
                    "$type": "ItemConfig",
                    "ID": 2
                },
                {
                    "$type": "ItemConfig",
                    "ID": 114001
                },
                {
                    "$type": "ItemConfig",
                    "ID": 114002
                },
                {
                    "$type": "ItemConfig",
                    "ID": 114003
                },
                {
                    "$type": "ItemConfig",
                    "ID": 181016
                }
            ]
        },
        {
            "MonsterTemplateID": 3002052,
            "WorldLevel": 6,
            "AvatarExpReward": 108,
            "DisplayItemList": [
                {
                    "$type": "ItemConfig",
                    "ID": 2
                },
                {
                    "$type": "ItemConfig",
                    "ID": 114001
                },
                {
                    "$type": "ItemConfig",
                    "ID": 114002
                },
                {
                    "$type": "ItemConfig",
                    "ID": 114003
                },
                {
                    "$type": "ItemConfig",
                    "ID": 181016
                }
            ]
        }
    ]
}