{
    "Name": "旧式井戸",
    "Desc": "至る所に見られる旧式の井戸。レンガ造りで水の品質を保つことができる。しかし吊りバケツの木製枠はそれほど丈夫ではない。",
    "Icon": "UI_Homeworld_Exterior_Ly_Decoration_Well_02_Lod0",
    "Rank": 2,
    "Type": [
        "景観"
    ],
    "Type2": [
        "大型オブジェクト"
    ],
    "Cost": 95,
    "Comfort": 30,
    "Source": [
        "洞天百貨で調度品設計図を購入して習得"
    ],
    "Recipe": {
        "Exp": 30,
        "Time": 43200,
        "Items": [
            {
                "id": 101002,
                "count": 4
            }
        ]
    }
}