{
    "Name": "木彫りのマント-「アランレンジャー」",
    "Desc": "着心地のいい精巧なマント。「アランナラ木彫り」の組み立てに使える。\\n熱心に他人の手助けをするお姉さんの衣装をモデルにして作られた。童話の中のアランナラはいつも森の中に出没しているため、当たり前のように茂る木の葉と花の間にパトロールし、この地域の安寧と静けさを守るアランナラもたくさんいる。そしてこれら熱心に友達を助けるアランナラたちに、レンジャーみのある称号を付けた：アランレンジャー",
    "Icon": "UI_Homeworld_Ani_Exterior_Common_Decoration_Prop_WoodAranaraCape_01_Vo",
    "Rank": 3,
    "Type": [
        "景観"
    ],
    "Type2": [
        "木彫りの部品"
    ],
    "Cost": null,
    "Comfort": null,
    "Source": [
        "期間限定イベントで獲得"
    ],
    "Recipe": {}
}