{
    "Id": 20031,
    "ContactsId": 1109,
    "ContactsType": 3,
    "ContactCamp": 1,
    "Name": "フック",
    "Signature": "...",
    "IconPath": "SpriteOutput/AvatarRoundIcon/Avatar/1109.png",
    "Sections": [
        {
            "Id": 2003100,
            "Messages": {
                "200310000": {
                    "Id": 200310000,
                    "ItemType": "Text",
                    "ItemContentID": null,
                    "ContactsID": null,
                    "Name": null,
                    "IconPath": null,
                    "MainText": "{NICKNAME}！",
                    "OptionText": null,
                    "NextItemIDList": [
                        200310001
                    ],
                    "Sender": "NPC"
                },
                "200310001": {
                    "Id": 200310001,
                    "ItemType": "Text",
                    "ItemContentID": null,
                    "ContactsID": null,
                    "Name": null,
                    "IconPath": null,
                    "MainText": "たすけて！",
                    "OptionText": null,
                    "NextItemIDList": [
                        200310002
                    ],
                    "Sender": "NPC"
                },
                "200310002": {
                    "Id": 200310002,
                    "ItemType": "Sticker",
                    "ItemContentID": 20005,
                    "ContactsID": null,
                    "Name": null,
                    "IconPath": null,
                    "MainText": "「うわ～ん」",
                    "OptionText": null,
                    "NextItemIDList": [
                        200310003
                    ],
                    "Sender": "NPC",
                    "ImagePath": ""
                },
                "200310003": {
                    "Id": 200310003,
                    "ItemType": "Text",
                    "ItemContentID": null,
                    "ContactsID": null,
                    "Name": null,
                    "IconPath": null,
                    "MainText": "<unbreak>5,000,000</unbreak>シールドあるか！あたしにくれ！",
                    "OptionText": null,
                    "NextItemIDList": [
                        200310005
                    ],
                    "Sender": "NPC"
                },
                "200310005": {
                    "Id": 200310005,
                    "ItemType": "Text",
                    "ItemContentID": null,
                    "ContactsID": null,
                    "Name": null,
                    "IconPath": null,
                    "MainText": "そんな大金、何に使う{F#の}{M#んだ}？",
                    "OptionText": "そんな大金、何に使う{F#の}{M#んだ}？",
                    "NextItemIDList": [
                        200310004
                    ],
                    "Sender": "Player"
                },
                "200310004": {
                    "Id": 200310004,
                    "ItemType": "Sticker",
                    "ItemContentID": 20007,
                    "ContactsID": null,
                    "Name": null,
                    "IconPath": null,
                    "MainText": "「困惑」",
                    "OptionText": "そんな大金、何に使う{F#の}{M#んだ}？",
                    "NextItemIDList": [
                        200310006
                    ],
                    "Sender": "PlayerAuto",
                    "ImagePath": ""
                },
                "200310006": {
                    "Id": 200310006,
                    "ItemType": "Text",
                    "ItemContentID": null,
                    "ContactsID": null,
                    "Name": null,
                    "IconPath": null,
                    "MainText": "オヤジがゆうかいされた！！！",
                    "OptionText": null,
                    "NextItemIDList": [
                        200310007
                    ],
                    "Sender": "NPC"
                },
                "200310007": {
                    "Id": 200310007,
                    "ItemType": "Text",
                    "ItemContentID": null,
                    "ContactsID": null,
                    "Name": null,
                    "IconPath": null,
                    "MainText": "だれだか知らないけど、さっきあたしにメッセージを送ってきたんだ！",
                    "OptionText": null,
                    "NextItemIDList": [
                        200310008
                    ],
                    "Sender": "NPC"
                },
                "200310008": {
                    "Id": 200310008,
                    "ItemType": "Text",
                    "ItemContentID": null,
                    "ContactsID": null,
                    "Name": null,
                    "IconPath": null,
                    "MainText": "<unbreak>5,000,000</unbreak>シールドあげないと、オヤジが危ないって言ってた！",
                    "OptionText": null,
                    "NextItemIDList": [
                        200310009
                    ],
                    "Sender": "NPC"
                },
                "200310009": {
                    "Id": 200310009,
                    "ItemType": "Text",
                    "ItemContentID": null,
                    "ContactsID": null,
                    "Name": null,
                    "IconPath": null,
                    "MainText": "……",
                    "OptionText": null,
                    "NextItemIDList": [
                        200310011,
                        200310019
                    ],
                    "Sender": "PlayerAuto"
                },
                "200310011": {
                    "Id": 200310011,
                    "ItemType": "Text",
                    "ItemContentID": null,
                    "ContactsID": null,
                    "Name": null,
                    "IconPath": null,
                    "MainText": "{F#私}{M#俺}もそんなに持ってない……",
                    "OptionText": "そんな大金持ってない",
                    "NextItemIDList": [
                        200310010
                    ],
                    "Sender": "Player"
                },
                "200310019": {
                    "Id": 200310019,
                    "ItemType": "Text",
                    "ItemContentID": null,
                    "ContactsID": null,
                    "Name": null,
                    "IconPath": null,
                    "MainText": "きっと詐欺だ{F#よ}{M#}……",
                    "OptionText": "詐欺だ{F#よ}",
                    "NextItemIDList": [
                        200310020
                    ],
                    "Sender": "Player"
                },
                "200310010": {
                    "Id": 200310010,
                    "ItemType": "Sticker",
                    "ItemContentID": 20005,
                    "ContactsID": null,
                    "Name": null,
                    "IconPath": null,
                    "MainText": "「うわ～ん」",
                    "OptionText": "そんな大金なんて持っていない",
                    "NextItemIDList": [
                        200310012
                    ],
                    "Sender": "PlayerAuto",
                    "ImagePath": ""
                },
                "200310020": {
                    "Id": 200310020,
                    "ItemType": "Text",
                    "ItemContentID": null,
                    "ContactsID": null,
                    "Name": null,
                    "IconPath": null,
                    "MainText": "まずはフェスマンにメッセージを送って確認{F#して}{M#するんだ}",
                    "OptionText": null,
                    "NextItemIDList": [
                        200310021
                    ],
                    "Sender": "PlayerAuto"
                },
                "200310012": {
                    "Id": 200310012,
                    "ItemType": "Text",
                    "ItemContentID": null,
                    "ContactsID": null,
                    "Name": null,
                    "IconPath": null,
                    "MainText": "ええ！！！",
                    "OptionText": null,
                    "NextItemIDList": [
                        200310013
                    ],
                    "Sender": "NPC"
                },
                "200310021": {
                    "Id": 200310021,
                    "ItemType": "Text",
                    "ItemContentID": null,
                    "ContactsID": null,
                    "Name": null,
                    "IconPath": null,
                    "MainText": "おお！！！",
                    "OptionText": null,
                    "NextItemIDList": [
                        200310022
                    ],
                    "Sender": "NPC"
                },
                "200310013": {
                    "Id": 200310013,
                    "ItemType": "Text",
                    "ItemContentID": null,
                    "ContactsID": null,
                    "Name": null,
                    "IconPath": null,
                    "MainText": "じゃあどうしよう！",
                    "OptionText": null,
                    "NextItemIDList": [
                        200310014
                    ],
                    "Sender": "NPC"
                },
                "200310022": {
                    "Id": 200310022,
                    "ItemType": "Text",
                    "ItemContentID": null,
                    "ContactsID": null,
                    "Name": null,
                    "IconPath": null,
                    "MainText": "なるほど！さすがめいよたいいん！",
                    "OptionText": null,
                    "NextItemIDList": [
                        200310023
                    ],
                    "Sender": "NPC"
                },
                "200310014": {
                    "Id": 200310014,
                    "ItemType": "Text",
                    "ItemContentID": null,
                    "ContactsID": null,
                    "Name": null,
                    "IconPath": null,
                    "MainText": "あたしとホールマスターでオヤジを助けなきゃ！",
                    "OptionText": null,
                    "NextItemIDList": [
                        200310015
                    ],
                    "Sender": "NPC"
                },
                "200310023": {
                    "Id": 200310023,
                    "ItemType": "Sticker",
                    "ItemContentID": 20008,
                    "ContactsID": null,
                    "Name": null,
                    "IconPath": null,
                    "MainText": "「びっくり」",
                    "OptionText": null,
                    "NextItemIDList": [
                        200310024
                    ],
                    "Sender": "NPC",
                    "ImagePath": ""
                },
                "200310015": {
                    "Id": 200310015,
                    "ItemType": "Sticker",
                    "ItemContentID": 20005,
                    "ContactsID": null,
                    "Name": null,
                    "IconPath": null,
                    "MainText": "「うわ～ん」",
                    "OptionText": null,
                    "NextItemIDList": [
                        200310016
                    ],
                    "Sender": "NPC",
                    "ImagePath": ""
                },
                "200310024": {
                    "Id": 200310024,
                    "ItemType": "Text",
                    "ItemContentID": null,
                    "ContactsID": null,
                    "Name": null,
                    "IconPath": null,
                    "MainText": "あ、オヤジが帰ってきた！",
                    "OptionText": null,
                    "NextItemIDList": [
                        200310025
                    ],
                    "Sender": "NPC"
                },
                "200310016": {
                    "Id": 200310016,
                    "ItemType": "Text",
                    "ItemContentID": null,
                    "ContactsID": null,
                    "Name": null,
                    "IconPath": null,
                    "MainText": "慌て{F#ないで}{M#るな}、それはきっと詐欺だ{F#よ}{M#}",
                    "OptionText": null,
                    "NextItemIDList": [
                        200310017
                    ],
                    "Sender": "PlayerAuto"
                },
                "200310025": {
                    "Id": 200310025,
                    "ItemType": "Text",
                    "ItemContentID": null,
                    "ContactsID": null,
                    "Name": null,
                    "IconPath": null,
                    "MainText": "大丈夫だった！よかった！うううううう",
                    "OptionText": null,
                    "NextItemIDList": [
                        200310026
                    ],
                    "Sender": "NPC"
                },
                "200310017": {
                    "Id": 200310017,
                    "ItemType": "Text",
                    "ItemContentID": null,
                    "ContactsID": null,
                    "Name": null,
                    "IconPath": null,
                    "MainText": "まずはフェスマンにメッセージを送って確認{F#して}{M#するんだ}",
                    "OptionText": null,
                    "NextItemIDList": [
                        200310024
                    ],
                    "Sender": "PlayerAuto"
                },
                "200310026": {
                    "Id": 200310026,
                    "ItemType": "Text",
                    "ItemContentID": null,
                    "ContactsID": null,
                    "Name": null,
                    "IconPath": null,
                    "MainText": "ありがとう、めいよたいいん！",
                    "OptionText": null,
                    "NextItemIDList": [
                        200310027
                    ],
                    "Sender": "NPC"
                },
                "200310027": {
                    "Id": 200310027,
                    "ItemType": "Sticker",
                    "ItemContentID": 20002,
                    "ContactsID": null,
                    "Name": null,
                    "IconPath": null,
                    "MainText": "「ありがとう」",
                    "OptionText": null,
                    "NextItemIDList": [],
                    "Sender": "NPC",
                    "ImagePath": ""
                }
            },
            "MessageStart": 200310000
        }
    ]
}