{
    "Id": 20046,
    "ContactsId": 1102,
    "ContactsType": 3,
    "ContactCamp": 1,
    "Name": "ゼーレ",
    "Signature": "...",
    "IconPath": "SpriteOutput/AvatarRoundIcon/Avatar/1102.png",
    "Sections": [
        {
            "Id": 2004600,
            "Messages": {
                "200460000": {
                    "Id": 200460000,
                    "ItemType": "Text",
                    "ItemContentID": null,
                    "ContactsID": null,
                    "Name": null,
                    "IconPath": null,
                    "MainText": "ねえ、いる？ちょっと聞きたいことが",
                    "OptionText": null,
                    "NextItemIDList": [
                        200460001
                    ],
                    "Sender": "NPC"
                },
                "200460001": {
                    "Id": 200460001,
                    "ItemType": "Text",
                    "ItemContentID": null,
                    "ContactsID": null,
                    "Name": null,
                    "IconPath": null,
                    "MainText": "アンタは普段",
                    "OptionText": null,
                    "NextItemIDList": [
                        200460002
                    ],
                    "Sender": "NPC"
                },
                "200460002": {
                    "Id": 200460002,
                    "ItemType": "Text",
                    "ItemContentID": null,
                    "ContactsID": null,
                    "Name": null,
                    "IconPath": null,
                    "MainText": "本を読んだりする？",
                    "OptionText": null,
                    "NextItemIDList": [
                        200460003,
                        200460006,
                        200460009
                    ],
                    "Sender": "NPC"
                },
                "200460003": {
                    "Id": 200460003,
                    "ItemType": "Text",
                    "ItemContentID": null,
                    "ContactsID": null,
                    "Name": null,
                    "IconPath": null,
                    "MainText": "読まない",
                    "OptionText": "読まない",
                    "NextItemIDList": [
                        200460004
                    ],
                    "Sender": "Player"
                },
                "200460006": {
                    "Id": 200460006,
                    "ItemType": "Text",
                    "ItemContentID": null,
                    "ContactsID": null,
                    "Name": null,
                    "IconPath": null,
                    "MainText": "たまにオンライン小説を読む",
                    "OptionText": "たまにオンライン小説を読む",
                    "NextItemIDList": [
                        200460007
                    ],
                    "Sender": "Player"
                },
                "200460009": {
                    "Id": 200460009,
                    "ItemType": "Text",
                    "ItemContentID": null,
                    "ContactsID": null,
                    "Name": null,
                    "IconPath": null,
                    "MainText": "{F#私}{M#俺}は色んなジャンルの本を読んでる{F#よ}{M#}",
                    "OptionText": "色んなジャンルの本を読んでる{F#よ}{M#}",
                    "NextItemIDList": [
                        200460010
                    ],
                    "Sender": "Player"
                },
                "200460004": {
                    "Id": 200460004,
                    "ItemType": "Text",
                    "ItemContentID": null,
                    "ContactsID": null,
                    "Name": null,
                    "IconPath": null,
                    "MainText": "そう",
                    "OptionText": null,
                    "NextItemIDList": [
                        200460005
                    ],
                    "Sender": "NPC"
                },
                "200460007": {
                    "Id": 200460007,
                    "ItemType": "Text",
                    "ItemContentID": null,
                    "ContactsID": null,
                    "Name": null,
                    "IconPath": null,
                    "MainText": "オンライン小説？面白いの？",
                    "OptionText": null,
                    "NextItemIDList": [
                        200460008
                    ],
                    "Sender": "NPC"
                },
                "200460010": {
                    "Id": 200460010,
                    "ItemType": "Text",
                    "ItemContentID": null,
                    "ContactsID": null,
                    "Name": null,
                    "IconPath": null,
                    "MainText": "スゴいわね",
                    "OptionText": null,
                    "NextItemIDList": [
                        200460011
                    ],
                    "Sender": "NPC"
                },
                "200460005": {
                    "Id": 200460005,
                    "ItemType": "Text",
                    "ItemContentID": null,
                    "ContactsID": null,
                    "Name": null,
                    "IconPath": null,
                    "MainText": "ワタシと同じレベルじゃない",
                    "OptionText": null,
                    "NextItemIDList": [
                        200460012
                    ],
                    "Sender": "NPC"
                },
                "200460008": {
                    "Id": 200460008,
                    "ItemType": "Text",
                    "ItemContentID": null,
                    "ContactsID": null,
                    "Name": null,
                    "IconPath": null,
                    "MainText": "はぁ、読書は好きじゃないの",
                    "OptionText": null,
                    "NextItemIDList": [
                        200460012
                    ],
                    "Sender": "NPC"
                },
                "200460011": {
                    "Id": 200460011,
                    "ItemType": "Text",
                    "ItemContentID": null,
                    "ContactsID": null,
                    "Name": null,
                    "IconPath": null,
                    "MainText": "はぁ、読書は好きじゃないの",
                    "OptionText": null,
                    "NextItemIDList": [
                        200460012
                    ],
                    "Sender": "NPC"
                },
                "200460012": {
                    "Id": 200460012,
                    "ItemType": "Text",
                    "ItemContentID": null,
                    "ContactsID": null,
                    "Name": null,
                    "IconPath": null,
                    "MainText": "体も頭も疲れるし",
                    "OptionText": null,
                    "NextItemIDList": [
                        200460013
                    ],
                    "Sender": "NPC"
                },
                "200460013": {
                    "Id": 200460013,
                    "ItemType": "Text",
                    "ItemContentID": null,
                    "ContactsID": null,
                    "Name": null,
                    "IconPath": null,
                    "MainText": "ページをめくったら、前の内容を忘れちゃうし",
                    "OptionText": null,
                    "NextItemIDList": [
                        200460014
                    ],
                    "Sender": "NPC"
                },
                "200460014": {
                    "Id": 200460014,
                    "ItemType": "Text",
                    "ItemContentID": null,
                    "ContactsID": null,
                    "Name": null,
                    "IconPath": null,
                    "MainText": "ブローニャはどうやってあれほどの本を読んだのかしら？",
                    "OptionText": null,
                    "NextItemIDList": [
                        200460015,
                        200460018
                    ],
                    "Sender": "NPC"
                },
                "200460015": {
                    "Id": 200460015,
                    "ItemType": "Text",
                    "ItemContentID": null,
                    "ContactsID": null,
                    "Name": null,
                    "IconPath": null,
                    "MainText": "ブローニャは子供の頃から英才教育を受けて来たから{F#ね}{M#な}",
                    "OptionText": "ブローニャは子供の頃から英才教育を受けて来たから{F#ね}{M#な}",
                    "NextItemIDList": [
                        200460016
                    ],
                    "Sender": "Player"
                },
                "200460018": {
                    "Id": 200460018,
                    "ItemType": "Text",
                    "ItemContentID": null,
                    "ContactsID": null,
                    "Name": null,
                    "IconPath": null,
                    "MainText": "何事も最初が一番難しいんだ{F#よ}",
                    "OptionText": "何事も最初が一番難しいんだ{F#よ}",
                    "NextItemIDList": [
                        200460019
                    ],
                    "Sender": "Player"
                },
                "200460016": {
                    "Id": 200460016,
                    "ItemType": "Text",
                    "ItemContentID": null,
                    "ContactsID": null,
                    "Name": null,
                    "IconPath": null,
                    "MainText": "フン、そうよね",
                    "OptionText": null,
                    "NextItemIDList": [
                        200460017
                    ],
                    "Sender": "NPC"
                },
                "200460019": {
                    "Id": 200460019,
                    "ItemType": "Text",
                    "ItemContentID": null,
                    "ContactsID": null,
                    "Name": null,
                    "IconPath": null,
                    "MainText": "確かにそうね",
                    "OptionText": null,
                    "NextItemIDList": [
                        200460020
                    ],
                    "Sender": "NPC"
                },
                "200460017": {
                    "Id": 200460017,
                    "ItemType": "Text",
                    "ItemContentID": null,
                    "ContactsID": null,
                    "Name": null,
                    "IconPath": null,
                    "MainText": "だから本の中身が頭に入らなくても普通よね、そうでしょ？",
                    "OptionText": null,
                    "NextItemIDList": [
                        200460021
                    ],
                    "Sender": "NPC"
                },
                "200460020": {
                    "Id": 200460020,
                    "ItemType": "Text",
                    "ItemContentID": null,
                    "ContactsID": null,
                    "Name": null,
                    "IconPath": null,
                    "MainText": "小さい頃は食べていくだけで必死だったのよ。本を読んでる時間なんてなかった",
                    "OptionText": null,
                    "NextItemIDList": [
                        200460021
                    ],
                    "Sender": "NPC"
                },
                "200460021": {
                    "Id": 200460021,
                    "ItemType": "Text",
                    "ItemContentID": null,
                    "ContactsID": null,
                    "Name": null,
                    "IconPath": null,
                    "MainText": "はぁ、ブローニャがたくさんの本を勧めてくれたんだけど",
                    "OptionText": null,
                    "NextItemIDList": [
                        200460022
                    ],
                    "Sender": "NPC"
                },
                "200460022": {
                    "Id": 200460022,
                    "ItemType": "Text",
                    "ItemContentID": null,
                    "ContactsID": null,
                    "Name": null,
                    "IconPath": null,
                    "MainText": "どれも最初の数ページをさらっと見ただけで",
                    "OptionText": null,
                    "NextItemIDList": [
                        200460023
                    ],
                    "Sender": "NPC"
                },
                "200460023": {
                    "Id": 200460023,
                    "ItemType": "Text",
                    "ItemContentID": null,
                    "ContactsID": null,
                    "Name": null,
                    "IconPath": null,
                    "MainText": "どうも頭に入らなくて、少しでも読むと眠たくなるのよ",
                    "OptionText": null,
                    "NextItemIDList": [
                        200460024
                    ],
                    "Sender": "NPC"
                },
                "200460024": {
                    "Id": 200460024,
                    "ItemType": "Text",
                    "ItemContentID": null,
                    "ContactsID": null,
                    "Name": null,
                    "IconPath": null,
                    "MainText": "あ、でも面白い本が一冊あったわ",
                    "OptionText": null,
                    "NextItemIDList": [
                        200460025
                    ],
                    "Sender": "NPC"
                },
                "200460025": {
                    "Id": 200460025,
                    "ItemType": "Text",
                    "ItemContentID": null,
                    "ContactsID": null,
                    "Name": null,
                    "IconPath": null,
                    "MainText": "『雪国冒険奇譚』って言うのよ。それも冒頭しか見てないけど、結構面白かったわ",
                    "OptionText": null,
                    "NextItemIDList": [
                        200460026
                    ],
                    "Sender": "NPC"
                },
                "200460026": {
                    "Id": 200460026,
                    "ItemType": "Text",
                    "ItemContentID": null,
                    "ContactsID": null,
                    "Name": null,
                    "IconPath": null,
                    "MainText": "まあ、お喋りはここまでにするわね。ちょっと愚痴っただけだから",
                    "OptionText": null,
                    "NextItemIDList": [
                        200460027
                    ],
                    "Sender": "NPC"
                },
                "200460027": {
                    "Id": 200460027,
                    "ItemType": "Text",
                    "ItemContentID": null,
                    "ContactsID": null,
                    "Name": null,
                    "IconPath": null,
                    "MainText": "本を読みに行くわ。できるだけ最後まで読めるようになってみせる",
                    "OptionText": null,
                    "NextItemIDList": [],
                    "Sender": "NPC"
                }
            },
            "MessageStart": 200460000
        }
    ]
}